pyvoice/__init__.py
pyvoice/__main__.py
pyvoice/custom_jedi_classes.py
pyvoice/generate_expressions.py
pyvoice/generate_imports.py
pyvoice/inference.py
pyvoice/logging.py
pyvoice/py.typed
pyvoice/server.py
pyvoice/speakify.py
pyvoice/text_edit_utils.py
pyvoice/transformations.py
pyvoice/types.py
pyvoice_language_server-0.1.4.dist-info/entry_points.txt
pyvoice_language_server-0.1.4.dist-info/LICENSE.rst
pyvoice_language_server-0.1.4.dist-info/WHEEL
pyvoice_language_server-0.1.4.dist-info/RECORD
pyvoice_language_server-0.1.4.dist-info/METADATA
