Metadata-Version: 2.1
Name: pyvoice-language-server
Version: 0.1.4
Summary: Experimental python language server for programming by voice
Home-page: https://github.com/PythonVoiceCodingPlugin
License: GPL-3.0
Author: mpourmpoulis
Author-email: 35875229+mpourmpoulis@users.noreply.github.com
Requires-Python: >=3.8,<4.0
Classifier: Development Status :: 1 - Planning
Classifier: License :: OSI Approved :: GNU General Public License v3 (GPLv3)
Classifier: Programming Language :: Python :: 3
Classifier: Programming Language :: Python :: 3.8
Classifier: Programming Language :: Python :: 3.9
Classifier: Programming Language :: Python :: 3.10
Classifier: Programming Language :: Python :: 3.11
Classifier: Programming Language :: Python :: 3.12
Requires-Dist: click (==8.1.7) ; python_version >= "3.8" and python_version < "4.0"
Requires-Dist: pygls (==1.3.1) ; python_version >= "3.8" and python_version < "4.0"
Requires-Dist: jedi (==0.19.1) ; python_version >= "3.8" and python_version < "4.0"
Requires-Dist: importlib-metadata (==8.0.0) ; python_version >= "3.8" and python_version < "4.0"
Requires-Dist: toml (==0.10.2) ; python_version >= "3.8" and python_version < "4.0"
Requires-Dist: requirements-detector (==1.0.3) ; python_version >= "3.8" and python_version < "4.0"
Requires-Dist: cachetools (==5.3.3) ; python_version >= "3.8" and python_version < "4.0"
Requires-Dist: setuptools (==69.5.1) ; python_version >= "3.8" and python_version < "4.0"
Requires-Dist: stdlibs (==2024.5.15) ; python_version >= "3.8" and python_version < "4.0"
Requires-Dist: colorama (==0.4.6) ; python_version >= "3.8" and python_version < "4.0" and platform_system == "Windows"
Requires-Dist: cattrs (==23.2.3) ; python_version >= "3.8" and python_version < "4.0"
Requires-Dist: lsprotocol (==2023.0.1) ; python_version >= "3.8" and python_version < "4.0"
Requires-Dist: parso (==0.8.4) ; python_version >= "3.8" and python_version < "4.0"
Requires-Dist: zipp (==3.19.2) ; python_version >= "3.8" and python_version < "4.0"
Requires-Dist: astroid (==2.15.8) ; python_version >= "3.8" and python_version < "4.0"
Requires-Dist: packaging (==21.3) ; python_version >= "3.8" and python_version < "4.0"
Requires-Dist: poetry-semver (==0.1.0) ; python_version >= "3.8" and python_version < "4.0"
Requires-Dist: attrs (==23.2.0) ; python_version >= "3.8" and python_version < "4.0"
Requires-Dist: exceptiongroup (==1.2.1) ; python_version >= "3.8" and python_version < "3.11"
Requires-Dist: typing-extensions (==4.12.2) ; python_version >= "3.8" and python_version < "3.11"
Requires-Dist: lazy-object-proxy (==1.10.0) ; python_version >= "3.8" and python_version < "4.0"
Requires-Dist: wrapt (==1.16.0) ; python_version >= "3.8" and python_version < "4.0"
Requires-Dist: pyparsing (==3.1.2) ; python_version >= "3.8" and python_version < "4.0"
Project-URL: Changelog, https://github.com/PythonVoiceCodingPlugin/pyvoice/releases
Project-URL: Caster Grammar, https://github.com/PythonVoiceCodingPlugin/pyvoice_caster
Project-URL: Chat, https://app.gitter.im/?updated=1.11.31#/room/#pythonvoicecodingpluginpyvoice:gitter.im
Project-URL: Repository, https://github.com/PythonVoiceCodingPlugin/pyvoice-language-server
Project-URL: Sublime Plugin, https://github.com/PythonVoiceCodingPlugin/LSP-pyvoice
Project-URL: Talon Grammar, https://github.com/PythonVoiceCodingPlugin/pyvoice_talon
Project-URL: VSCode Marketplace, https://marketplace.visualstudio.com/items?itemName=mpourmpoulis.pyvoice
